{
    "name": "15.10.20",
    "tracks": [
        {
            "name": "I Only Wanted You",
            "album": "Dreams",
            "artists": [
                "Sofie Winterson"
            ]
        },
        {
            "name": "Strange Emotion",
            "album": "Pull My Hair Back",
            "artists": [
                "Jessy Lanza"
            ]
        },
        {
            "name": "Majorette",
            "album": "Thank Your Lucky Stars",
            "artists": [
                "Beach House"
            ]
        },
        {
            "name": "All the Same",
            "album": "Fading Frontier",
            "artists": [
                "Deerhunter"
            ]
        },
        {
            "name": "The Hollow Sound of the Morning Chimes",
            "album": "The Hollow Sound of the Morning Chimes",
            "artists": [
                "TOPS"
            ]
        },
        {
            "name": "I Follow You",
            "album": "Melody's Echo Chamber",
            "artists": [
                "Melody's Echo Chamber"
            ]
        },
        {
            "name": "Leonie",
            "album": "Zentropy",
            "artists": [
                "Frankie Cosmos"
            ]
        },
        {
            "name": "Cappo",
            "album": "Nouns",
            "artists": [
                "No Age"
            ]
        },
        {
            "name": "Almost Crimes - (Radio Kills Remix) / Broken Social Scene",
            "album": "You Forgot It In People",
            "artists": [
                "Broken Social Scene"
            ]
        },
        {
            "name": "Rollercoaster Rider",
            "album": "Overgrown Path",
            "artists": [
                "chris cohen"
            ]
        }
    ]
}