{
    "name": "17.08.14",
    "tracks": [
        {
            "name": "The Big Country - Remastered & Expanded Version",
            "album": "The Name Of This Band Is Talking Heads (Expanded & Remastered)",
            "artists": [
                "Talking Heads"
            ]
        },
        {
            "name": "Temptation - 7\" Version; 2015 Remaster",
            "album": "Singles (Remastered)",
            "artists": [
                "New Order"
            ]
        },
        {
            "name": "Starman - 2012 Remaster",
            "album": "The Rise And Fall Of Ziggy Stardust And The Spiders From Mars (2012 Remastered Version)",
            "artists": [
                "David Bowie"
            ]
        },
        {
            "name": "Today More Than Any Other Day",
            "album": "More Than Any Other Day",
            "artists": [
                "Ought"
            ]
        },
        {
            "name": "Anything Could Happen",
            "album": "Compilation",
            "artists": [
                "The Clean"
            ]
        },
        {
            "name": "1937 State Park",
            "album": "Teens of Denial",
            "artists": [
                "Car Seat Headrest"
            ]
        },
        {
            "name": "Upon This Tidal Wave of Young Blood",
            "album": "Clap Your Hands Say Yeah",
            "artists": [
                "Clap Your Hands Say Yeah"
            ]
        },
        {
            "name": "Raised Eyebrows",
            "album": "Crazy Rhythms",
            "artists": [
                "The Feelies"
            ]
        },
        {
            "name": "Unsatisfied",
            "album": "Let It Be [Expanded Edition]",
            "artists": [
                "The Replacements"
            ]
        },
        {
            "name": "Watchmaker",
            "album": "Such Friends Are Dangerous",
            "artists": [
                "Excuse 17"
            ]
        },
        {
            "name": "All My Friends",
            "album": "Sound Of Silver",
            "artists": [
                "LCD Soundsystem"
            ]
        }
    ]
}